mee6_py_api/__init__.py
mee6_py_api/api.py
mee6_py_api/config.py
mee6_py_api/constants.py
mee6_py_api/exceptions.py
mee6_py_api/plugins/__init__.py
mee6_py_api/plugins/levels.py
mee6_py_api/utils/__init__.py
mee6_py_api/utils/logging.py
mee6_py_api-0.0.1.dist-info/LICENSE
mee6_py_api-0.0.1.dist-info/METADATA
mee6_py_api-0.0.1.dist-info/WHEEL
mee6_py_api-0.0.1.dist-info/top_level.txt
mee6_py_api-0.0.1.dist-info/RECORD
