Metadata-Version: 2.1
Name: mee6-py-api
Version: 0.0.1
Summary: Unofficial Python API for the Mee6 Discord bot
Home-page: https://github.com/hyperevo/mee6-py-api
Author: Tommy Mckinnon
Author-email: admin@hyperevo.com
License: MIT
Keywords: mee6 python api
Platform: UNKNOWN
Classifier: Development Status :: 5 - Production/Stable
Classifier: Intended Audience :: Developers
Classifier: License :: OSI Approved :: MIT License
Classifier: Natural Language :: English
Classifier: Programming Language :: Python :: 3
Classifier: Programming Language :: Python :: 3.6
Classifier: Programming Language :: Python :: 3.7
Requires-Python: >=3.6,<4
Requires-Dist: aiohttp (<4,>=3)
